{
  "$schema": "https://static.modelcontextprotocol.io/schemas/2025-12-11/server.schema.json",
  "name": "io.github.kryptobaseddev/cleo-mcp-server",
  "title": "CLEO MCP Server",
  "description": "Task management for solo developers and AI coding agents — CQRS pattern, 200 operations across 10 domains",
  "version": "2026.3.23",
  "websiteUrl": "https://github.com/kryptobaseddev/cleo",
  "repository": {
    "url": "https://github.com/kryptobaseddev/cleo.git",
    "source": "github"
  },
  "packages": [
    {
      "registryType": "npm",
      "identifier": "@cleocode/cleo",
      "version": "2026.3.23",
      "transport": {
        "type": "stdio"
      },
      "packageArguments": [
        {
          "type": "positional",
          "value": "--mcp-server",
          "description": "Start the MCP stdio server instead of the CLI"
        }
      ],
      "environmentVariables": [
        {
          "name": "CLEO_PROJECT_DIR",
          "description": "Path to CLEO project directory (must contain .cleo/ folder)",
          "isRequired": false
        }
      ]
    }
  ],
  "_meta": {
    "io.modelcontextprotocol.registry/publisher-provided": {
      "tools": [
        {
          "name": "query",
          "description": "Read-only operations across 10 domains: tasks, session, orchestrate, memory, pipeline, check, admin, tools, nexus, sticky"
        },
        {
          "name": "mutate",
          "description": "Write operations across 10 domains: tasks, session, orchestrate, memory, pipeline, check, admin, tools, nexus, sticky"
        }
      ],
      "features": [
        "CQRS 2-gateway pattern (94% token reduction vs traditional MCP tool approach)",
        "200 operations across 10 canonical domains",
        "Anti-hallucination validation on all task operations",
        "Atomic file operations with backup and rollback"
      ],
      "categories": ["developer-tools", "task-management", "ai-agents"]
    }
  }
}
