{"nodes": [{"id": "ct_adr_recorder_skill", "label": "ct-adr-recorder skill", "file_type": "document", "source_file": "/mnt/projects/cleocode/packages/skills/skills/ct-adr-recorder/SKILL.md", "source_location": null, "source_url": null, "captured_at": null, "author": null, "contributor": null}, {"id": "adr_001", "label": "ADR-001 generated from consensus verdict", "file_type": "rationale", "source_file": "/mnt/projects/cleocode/packages/skills/skills/ct-adr-recorder/SKILL.md", "source_location": null, "source_url": null, "captured_at": null, "author": null, "contributor": null}, {"id": "adr_002", "label": "ADR-002 consensus_manifest_id required", "file_type": "rationale", "source_file": "/mnt/projects/cleocode/packages/skills/skills/ct-adr-recorder/SKILL.md", "source_location": null, "source_url": null, "captured_at": null, "author": null, "contributor": null}, {"id": "adr_003", "label": "ADR-003 HITL approval required", "file_type": "rationale", "source_file": "/mnt/projects/cleocode/packages/skills/skills/ct-adr-recorder/SKILL.md", "source_location": null, "source_url": null, "captured_at": null, "author": null, "contributor": null}, {"id": "adr_004", "label": "ADR-004 canonical sections required", "file_type": "rationale", "source_file": "/mnt/projects/cleocode/packages/skills/skills/ct-adr-recorder/SKILL.md", "source_location": null, "source_url": null, "captured_at": null, "author": null, "contributor": null}, {"id": "adr_005", "label": "ADR-005 supersession cascade", "file_type": "rationale", "source_file": "/mnt/projects/cleocode/packages/skills/skills/ct-adr-recorder/SKILL.md", "source_location": null, "source_url": null, "captured_at": null, "author": null, "contributor": null}, {"id": "adr_006", "label": "ADR-006 SQLite decisions table persistence", "file_type": "rationale", "source_file": "/mnt/projects/cleocode/packages/skills/skills/ct-adr-recorder/SKILL.md", "source_location": null, "source_url": null, "captured_at": null, "author": null, "contributor": null}, {"id": "adr_007", "label": "ADR-007 agent_type:decision required", "file_type": "rationale", "source_file": "/mnt/projects/cleocode/packages/skills/skills/ct-adr-recorder/SKILL.md", "source_location": null, "source_url": null, "captured_at": null, "author": null, "contributor": null}, {"id": "adr_008", "label": "ADR-008 blocks Spec stage until accepted", "file_type": "rationale", "source_file": "/mnt/projects/cleocode/packages/skills/skills/ct-adr-recorder/SKILL.md", "source_location": null, "source_url": null, "captured_at": null, "author": null, "contributor": null}, {"id": "adr_validateArchitectureDecisionProtocol", "label": "validateArchitectureDecisionProtocol()", "file_type": "code", "source_file": "/mnt/projects/cleocode/packages/skills/skills/ct-adr-recorder/SKILL.md", "source_location": null, "source_url": null, "captured_at": null, "author": null, "contributor": null}, {"id": "adr_check_protocol_cmd", "label": "cleo check protocol --protocolType architecture-decision", "file_type": "code", "source_file": "/mnt/projects/cleocode/packages/skills/skills/ct-adr-recorder/SKILL.md", "source_location": null, "source_url": null, "captured_at": null, "author": null, "contributor": null}, {"id": "adr_lifecycle_status", "label": "ADR Status Lifecycle (proposed/accepted/superseded/deprecated)", "file_type": "document", "source_file": "/mnt/projects/cleocode/packages/skills/skills/ct-adr-recorder/SKILL.md", "source_location": null, "source_url": null, "captured_at": null, "author": null, "contributor": null}], "edges": [{"source": "ct_adr_recorder_skill", "target": "adr_001", "relation": "references", "confidence": "EXTRACTED", "confidence_score": 1.0, "source_file": "/mnt/projects/cleocode/packages/skills/skills/ct-adr-recorder/SKILL.md", "source_location": null, "weight": 1.0}, {"source": "ct_adr_recorder_skill", "target": "adr_002", "relation": "references", "confidence": "EXTRACTED", "confidence_score": 1.0, "source_file": "/mnt/projects/cleocode/packages/skills/skills/ct-adr-recorder/SKILL.md", "source_location": null, "weight": 1.0}, {"source": "ct_adr_recorder_skill", "target": "adr_003", "relation": "references", "confidence": "EXTRACTED", "confidence_score": 1.0, "source_file": "/mnt/projects/cleocode/packages/skills/skills/ct-adr-recorder/SKILL.md", "source_location": null, "weight": 1.0}, {"source": "ct_adr_recorder_skill", "target": "adr_004", "relation": "references", "confidence": "EXTRACTED", "confidence_score": 1.0, "source_file": "/mnt/projects/cleocode/packages/skills/skills/ct-adr-recorder/SKILL.md", "source_location": null, "weight": 1.0}, {"source": "ct_adr_recorder_skill", "target": "adr_005", "relation": "references", "confidence": "EXTRACTED", "confidence_score": 1.0, "source_file": "/mnt/projects/cleocode/packages/skills/skills/ct-adr-recorder/SKILL.md", "source_location": null, "weight": 1.0}, {"source": "ct_adr_recorder_skill", "target": "adr_006", "relation": "references", "confidence": "EXTRACTED", "confidence_score": 1.0, "source_file": "/mnt/projects/cleocode/packages/skills/skills/ct-adr-recorder/SKILL.md", "source_location": null, "weight": 1.0}, {"source": "ct_adr_recorder_skill", "target": "adr_007", "relation": "references", "confidence": "EXTRACTED", "confidence_score": 1.0, "source_file": "/mnt/projects/cleocode/packages/skills/skills/ct-adr-recorder/SKILL.md", "source_location": null, "weight": 1.0}, {"source": "ct_adr_recorder_skill", "target": "adr_008", "relation": "references", "confidence": "EXTRACTED", "confidence_score": 1.0, "source_file": "/mnt/projects/cleocode/packages/skills/skills/ct-adr-recorder/SKILL.md", "source_location": null, "weight": 1.0}, {"source": "adr_001", "target": "adr_validateArchitectureDecisionProtocol", "relation": "references", "confidence": "EXTRACTED", "confidence_score": 1.0, "source_file": "/mnt/projects/cleocode/packages/skills/skills/ct-adr-recorder/SKILL.md", "source_location": null, "weight": 1.0}, {"source": "adr_check_protocol_cmd", "target": "adr_validateArchitectureDecisionProtocol", "relation": "calls", "confidence": "INFERRED", "confidence_score": 0.95, "source_file": "/mnt/projects/cleocode/packages/skills/skills/ct-adr-recorder/SKILL.md", "source_location": null, "weight": 0.95}, {"source": "ct_adr_recorder_skill", "target": "adr_lifecycle_status", "relation": "references", "confidence": "EXTRACTED", "confidence_score": 1.0, "source_file": "/mnt/projects/cleocode/packages/skills/skills/ct-adr-recorder/SKILL.md", "source_location": null, "weight": 1.0}, {"source": "ct_adr_recorder_skill", "target": "adr_cascade_doc", "relation": "references", "confidence": "EXTRACTED", "confidence_score": 1.0, "source_file": "/mnt/projects/cleocode/packages/skills/skills/ct-adr-recorder/SKILL.md", "source_location": null, "weight": 1.0}, {"source": "ct_adr_recorder_skill", "target": "adr_examples_doc", "relation": "references", "confidence": "EXTRACTED", "confidence_score": 1.0, "source_file": "/mnt/projects/cleocode/packages/skills/skills/ct-adr-recorder/SKILL.md", "source_location": null, "weight": 1.0}, {"source": "ct_adr_recorder_skill", "target": "ct_consensus_voter_skill", "relation": "conceptually_related_to", "confidence": "INFERRED", "confidence_score": 0.95, "source_file": "/mnt/projects/cleocode/packages/skills/skills/ct-adr-recorder/SKILL.md", "source_location": null, "weight": 0.95}], "hyperedges": []}