{"nodes": [{"id": "lafs_changelog", "label": "LAFS CHANGELOG", "file_type": "document", "source_file": "packages/lafs/CHANGELOG.md", "source_location": null, "source_url": null, "captured_at": null, "author": null, "contributor": null}, {"id": "lafs_v2026_4_3_native_validator", "label": "v2026.4.3: Native Rust validator (lafs-napi)", "file_type": "document", "source_file": "packages/lafs/CHANGELOG.md", "source_location": null, "source_url": null, "captured_at": "2026-04-06", "author": null, "contributor": null}, {"id": "lafs_v2026_4_0_calver", "label": "v2026.4.0: CalVer adoption + monorepo consolidation", "file_type": "document", "source_file": "packages/lafs/CHANGELOG.md", "source_location": null, "source_url": null, "captured_at": "2026-04-03", "author": null, "contributor": null}, {"id": "lafs_v1_8_0_error_with_result", "label": "v1.8.0: Error envelopes MAY include result", "file_type": "document", "source_file": "packages/lafs/CHANGELOG.md", "source_location": null, "source_url": null, "captured_at": "2026-03-19", "author": null, "contributor": null}, {"id": "lafs_v1_7_0_mvi_projection", "label": "v1.7.0: MVI projection + agentAction + RFC 9457 bridge", "file_type": "document", "source_file": "packages/lafs/CHANGELOG.md", "source_location": null, "source_url": null, "captured_at": "2026-03-15", "author": null, "contributor": null}, {"id": "lafs_v1_5_0_field_extraction", "label": "v1.5.0: Field extraction + E_FIELD_CONFLICT", "file_type": "document", "source_file": "packages/lafs/CHANGELOG.md", "source_location": null, "source_url": null, "captured_at": "2026-02-26", "author": null, "contributor": null}, {"id": "lafs_v1_3_0_a2a_compliance", "label": "v1.3.0: A2A v1.0+ compliance (extensions/lifecycle/bindings)", "file_type": "document", "source_file": "packages/lafs/CHANGELOG.md", "source_location": null, "source_url": null, "captured_at": "2026-02-20", "author": null, "contributor": null}, {"id": "lafs_v1_1_0_ops_reliability", "label": "v1.1.0: Ops/Reliability (health/shutdown/circuit-breaker)", "file_type": "document", "source_file": "packages/lafs/CHANGELOG.md", "source_location": null, "source_url": null, "captured_at": "2026-02-16", "author": null, "contributor": null}, {"id": "lafs_v1_0_0_production", "label": "v1.0.0: Token budgets + discovery + MCP", "file_type": "document", "source_file": "packages/lafs/CHANGELOG.md", "source_location": null, "source_url": null, "captured_at": "2026-02-16", "author": null, "contributor": null}, {"id": "lafs_napi_crate", "label": "lafs-napi (Rust napi-rs binding)", "file_type": "code", "source_file": "packages/lafs/CHANGELOG.md", "source_location": "crates/lafs-napi/", "source_url": null, "captured_at": null, "author": null, "contributor": null}, {"id": "lafs_core_crate", "label": "lafs-core (pure Rust library)", "file_type": "code", "source_file": "packages/lafs/CHANGELOG.md", "source_location": null, "source_url": null, "captured_at": null, "author": null, "contributor": null}, {"id": "lafs_rfc9457", "label": "RFC 9457 Problem Details", "file_type": "paper", "source_file": "packages/lafs/CHANGELOG.md", "source_location": null, "source_url": null, "captured_at": null, "author": null, "contributor": null}], "edges": [{"source": "lafs_changelog", "target": "lafs_v2026_4_3_native_validator", "relation": "references", "confidence": "EXTRACTED", "confidence_score": 1.0, "source_file": "packages/lafs/CHANGELOG.md", "source_location": null, "weight": 1.0}, {"source": "lafs_changelog", "target": "lafs_v2026_4_0_calver", "relation": "references", "confidence": "EXTRACTED", "confidence_score": 1.0, "source_file": "packages/lafs/CHANGELOG.md", "source_location": null, "weight": 1.0}, {"source": "lafs_changelog", "target": "lafs_v1_8_0_error_with_result", "relation": "references", "confidence": "EXTRACTED", "confidence_score": 1.0, "source_file": "packages/lafs/CHANGELOG.md", "source_location": null, "weight": 1.0}, {"source": "lafs_changelog", "target": "lafs_v1_7_0_mvi_projection", "relation": "references", "confidence": "EXTRACTED", "confidence_score": 1.0, "source_file": "packages/lafs/CHANGELOG.md", "source_location": null, "weight": 1.0}, {"source": "lafs_changelog", "target": "lafs_v1_5_0_field_extraction", "relation": "references", "confidence": "EXTRACTED", "confidence_score": 1.0, "source_file": "packages/lafs/CHANGELOG.md", "source_location": null, "weight": 1.0}, {"source": "lafs_changelog", "target": "lafs_v1_3_0_a2a_compliance", "relation": "references", "confidence": "EXTRACTED", "confidence_score": 1.0, "source_file": "packages/lafs/CHANGELOG.md", "source_location": null, "weight": 1.0}, {"source": "lafs_changelog", "target": "lafs_v1_1_0_ops_reliability", "relation": "references", "confidence": "EXTRACTED", "confidence_score": 1.0, "source_file": "packages/lafs/CHANGELOG.md", "source_location": null, "weight": 1.0}, {"source": "lafs_changelog", "target": "lafs_v1_0_0_production", "relation": "references", "confidence": "EXTRACTED", "confidence_score": 1.0, "source_file": "packages/lafs/CHANGELOG.md", "source_location": null, "weight": 1.0}, {"source": "lafs_v2026_4_3_native_validator", "target": "lafs_napi_crate", "relation": "references", "confidence": "EXTRACTED", "confidence_score": 1.0, "source_file": "packages/lafs/CHANGELOG.md", "source_location": null, "weight": 1.0}, {"source": "lafs_v2026_4_3_native_validator", "target": "lafs_core_crate", "relation": "references", "confidence": "EXTRACTED", "confidence_score": 1.0, "source_file": "packages/lafs/CHANGELOG.md", "source_location": null, "weight": 1.0}, {"source": "lafs_v2026_4_3_native_validator", "target": "lafs_native_loader", "relation": "references", "confidence": "EXTRACTED", "confidence_score": 1.0, "source_file": "packages/lafs/CHANGELOG.md", "source_location": null, "weight": 1.0}, {"source": "lafs_v1_7_0_mvi_projection", "target": "lafs_mvi_projection_ts", "relation": "references", "confidence": "EXTRACTED", "confidence_score": 1.0, "source_file": "packages/lafs/CHANGELOG.md", "source_location": null, "weight": 1.0}, {"source": "lafs_v1_7_0_mvi_projection", "target": "lafs_problem_details", "relation": "references", "confidence": "EXTRACTED", "confidence_score": 1.0, "source_file": "packages/lafs/CHANGELOG.md", "source_location": null, "weight": 1.0}, {"source": "lafs_v1_7_0_mvi_projection", "target": "lafs_agent_action_semantics", "relation": "references", "confidence": "EXTRACTED", "confidence_score": 1.0, "source_file": "packages/lafs/CHANGELOG.md", "source_location": null, "weight": 1.0}, {"source": "lafs_v1_5_0_field_extraction", "target": "lafs_field_extraction", "relation": "references", "confidence": "EXTRACTED", "confidence_score": 1.0, "source_file": "packages/lafs/CHANGELOG.md", "source_location": null, "weight": 1.0}, {"source": "lafs_v1_3_0_a2a_compliance", "target": "lafs_a2a_extensions", "relation": "references", "confidence": "EXTRACTED", "confidence_score": 1.0, "source_file": "packages/lafs/CHANGELOG.md", "source_location": null, "weight": 1.0}, {"source": "lafs_v1_3_0_a2a_compliance", "target": "lafs_a2a_task_lifecycle", "relation": "references", "confidence": "EXTRACTED", "confidence_score": 1.0, "source_file": "packages/lafs/CHANGELOG.md", "source_location": null, "weight": 1.0}, {"source": "lafs_v1_3_0_a2a_compliance", "target": "lafs_a2a_bindings_jsonrpc", "relation": "references", "confidence": "EXTRACTED", "confidence_score": 1.0, "source_file": "packages/lafs/CHANGELOG.md", "source_location": null, "weight": 1.0}, {"source": "lafs_v1_3_0_a2a_compliance", "target": "lafs_a2a_bindings_http", "relation": "references", "confidence": "EXTRACTED", "confidence_score": 1.0, "source_file": "packages/lafs/CHANGELOG.md", "source_location": null, "weight": 1.0}, {"source": "lafs_v1_3_0_a2a_compliance", "target": "lafs_a2a_bindings_grpc", "relation": "references", "confidence": "EXTRACTED", "confidence_score": 1.0, "source_file": "packages/lafs/CHANGELOG.md", "source_location": null, "weight": 1.0}, {"source": "lafs_v1_1_0_ops_reliability", "target": "lafs_health_module", "relation": "references", "confidence": "EXTRACTED", "confidence_score": 1.0, "source_file": "packages/lafs/CHANGELOG.md", "source_location": null, "weight": 1.0}, {"source": "lafs_v1_1_0_ops_reliability", "target": "lafs_shutdown_module", "relation": "references", "confidence": "EXTRACTED", "confidence_score": 1.0, "source_file": "packages/lafs/CHANGELOG.md", "source_location": null, "weight": 1.0}, {"source": "lafs_v1_1_0_ops_reliability", "target": "lafs_circuit_breaker", "relation": "references", "confidence": "EXTRACTED", "confidence_score": 1.0, "source_file": "packages/lafs/CHANGELOG.md", "source_location": null, "weight": 1.0}, {"source": "lafs_v1_0_0_production", "target": "lafs_token_budget_signaling", "relation": "references", "confidence": "EXTRACTED", "confidence_score": 1.0, "source_file": "packages/lafs/CHANGELOG.md", "source_location": null, "weight": 1.0}, {"source": "lafs_v1_0_0_production", "target": "lafs_discovery_middleware", "relation": "references", "confidence": "EXTRACTED", "confidence_score": 1.0, "source_file": "packages/lafs/CHANGELOG.md", "source_location": null, "weight": 1.0}, {"source": "lafs_napi_crate", "target": "lafs_core_crate", "relation": "references", "confidence": "EXTRACTED", "confidence_score": 1.0, "source_file": "packages/lafs/CHANGELOG.md", "source_location": null, "weight": 1.0}], "hyperedges": []}