{"nodes": [{"id": "removemcpserver_function", "label": "removeMcpServer", "file_type": "document", "source_file": "packages/caamp/docs/api/functions/removeMcpServer.html", "source_location": "src/core/mcp/reader.ts:146", "source_url": "https://github.com/kryptobaseddev/caamp/blob/0d62470154a48a98507384406aa65fe4b90d4870/src/core/mcp/reader.ts#L146", "captured_at": null, "author": null, "contributor": null}], "edges": [{"source": "removemcpserver_function", "target": "removemcpfromlock_function", "relation": "calls", "confidence": "INFERRED", "confidence_score": 0.75, "source_file": "packages/caamp/docs/api/functions/removeMcpServer.html", "source_location": null, "weight": 1.0}, {"source": "removemcpserver_function", "target": "caamp_module_mcp", "relation": "references", "confidence": "EXTRACTED", "confidence_score": 1.0, "source_file": "packages/caamp/docs/api/functions/removeMcpServer.html", "source_location": "reader.ts:146", "weight": 1.0}], "hyperedges": []}