{"nodes": [{"id": "mnt_projects_cleocode_packages_lafs_docs_vision_md", "label": "VISION.md", "file_type": "document", "source_file": "/mnt/projects/cleocode/packages/lafs/docs/VISION.md", "source_location": "L1"}, {"id": "docs_vision_lafs_vision", "label": "LAFS Vision", "file_type": "document", "source_file": "/mnt/projects/cleocode/packages/lafs/docs/VISION.md", "source_location": "L1"}, {"id": "docs_vision_the_problem", "label": "The Problem", "file_type": "document", "source_file": "/mnt/projects/cleocode/packages/lafs/docs/VISION.md", "source_location": "L5"}, {"id": "docs_vision_what_lafs_provides_for_agents", "label": "What LAFS provides for agents", "file_type": "document", "source_file": "/mnt/projects/cleocode/packages/lafs/docs/VISION.md", "source_location": "L16"}, {"id": "docs_vision_before_lafs", "label": "Before LAFS", "file_type": "document", "source_file": "/mnt/projects/cleocode/packages/lafs/docs/VISION.md", "source_location": "L27"}, {"id": "docs_vision_codeblock_1", "label": "code:typescript (// Service A)", "file_type": "document", "source_file": "/mnt/projects/cleocode/packages/lafs/docs/VISION.md", "source_location": "L31"}, {"id": "docs_vision_after_lafs", "label": "After LAFS", "file_type": "document", "source_file": "/mnt/projects/cleocode/packages/lafs/docs/VISION.md", "source_location": "L51"}, {"id": "docs_vision_codeblock_2", "label": "code:typescript (// Service A, B, and C all return LAFS envelopes)", "file_type": "document", "source_file": "/mnt/projects/cleocode/packages/lafs/docs/VISION.md", "source_location": "L55"}, {"id": "docs_vision_who_lafs_is_for", "label": "Who LAFS is for", "file_type": "document", "source_file": "/mnt/projects/cleocode/packages/lafs/docs/VISION.md", "source_location": "L67"}, {"id": "docs_vision_design_principles", "label": "Design principles", "file_type": "document", "source_file": "/mnt/projects/cleocode/packages/lafs/docs/VISION.md", "source_location": "L78"}, {"id": "docs_vision_boundary_model", "label": "Boundary model", "file_type": "document", "source_file": "/mnt/projects/cleocode/packages/lafs/docs/VISION.md", "source_location": "L88"}, {"id": "docs_vision_next_steps", "label": "Next steps", "file_type": "document", "source_file": "/mnt/projects/cleocode/packages/lafs/docs/VISION.md", "source_location": "L96"}, {"id": "docs_vision_complementary_positioning", "label": "Complementary positioning", "file_type": "document", "source_file": "/mnt/projects/cleocode/packages/lafs/docs/VISION.md", "source_location": "L102"}], "edges": [{"source": "mnt_projects_cleocode_packages_lafs_docs_vision_md", "target": "docs_vision_lafs_vision", "relation": "contains", "confidence": "EXTRACTED", "source_file": "/mnt/projects/cleocode/packages/lafs/docs/VISION.md", "source_location": "L1", "weight": 1.0}, {"source": "docs_vision_lafs_vision", "target": "docs_vision_the_problem", "relation": "contains", "confidence": "EXTRACTED", "source_file": "/mnt/projects/cleocode/packages/lafs/docs/VISION.md", "source_location": "L5", "weight": 1.0}, {"source": "docs_vision_lafs_vision", "target": "docs_vision_what_lafs_provides_for_agents", "relation": "contains", "confidence": "EXTRACTED", "source_file": "/mnt/projects/cleocode/packages/lafs/docs/VISION.md", "source_location": "L16", "weight": 1.0}, {"source": "docs_vision_what_lafs_provides_for_agents", "target": "docs_vision_before_lafs", "relation": "contains", "confidence": "EXTRACTED", "source_file": "/mnt/projects/cleocode/packages/lafs/docs/VISION.md", "source_location": "L27", "weight": 1.0}, {"source": "docs_vision_before_lafs", "target": "docs_vision_codeblock_1", "relation": "contains", "confidence": "EXTRACTED", "source_file": "/mnt/projects/cleocode/packages/lafs/docs/VISION.md", "source_location": "L31", "weight": 1.0}, {"source": "docs_vision_what_lafs_provides_for_agents", "target": "docs_vision_after_lafs", "relation": "contains", "confidence": "EXTRACTED", "source_file": "/mnt/projects/cleocode/packages/lafs/docs/VISION.md", "source_location": "L51", "weight": 1.0}, {"source": "docs_vision_after_lafs", "target": "docs_vision_codeblock_2", "relation": "contains", "confidence": "EXTRACTED", "source_file": "/mnt/projects/cleocode/packages/lafs/docs/VISION.md", "source_location": "L55", "weight": 1.0}, {"source": "docs_vision_lafs_vision", "target": "docs_vision_who_lafs_is_for", "relation": "contains", "confidence": "EXTRACTED", "source_file": "/mnt/projects/cleocode/packages/lafs/docs/VISION.md", "source_location": "L67", "weight": 1.0}, {"source": "docs_vision_lafs_vision", "target": "docs_vision_design_principles", "relation": "contains", "confidence": "EXTRACTED", "source_file": "/mnt/projects/cleocode/packages/lafs/docs/VISION.md", "source_location": "L78", "weight": 1.0}, {"source": "docs_vision_lafs_vision", "target": "docs_vision_boundary_model", "relation": "contains", "confidence": "EXTRACTED", "source_file": "/mnt/projects/cleocode/packages/lafs/docs/VISION.md", "source_location": "L88", "weight": 1.0}, {"source": "docs_vision_lafs_vision", "target": "docs_vision_next_steps", "relation": "contains", "confidence": "EXTRACTED", "source_file": "/mnt/projects/cleocode/packages/lafs/docs/VISION.md", "source_location": "L96", "weight": 1.0}, {"source": "docs_vision_lafs_vision", "target": "docs_vision_complementary_positioning", "relation": "contains", "confidence": "EXTRACTED", "source_file": "/mnt/projects/cleocode/packages/lafs/docs/VISION.md", "source_location": "L102", "weight": 1.0}], "input_tokens": 0, "output_tokens": 0}